LICENCE
MANIFEST.in
README.md
requirements.txt
setup.py
fanta/__init__.py
fanta/client.py
fanta/dispatcher.py
fanta/exceptions.py
fanta/http.py
fanta/ratelimiter.py
fanta/shard.py
fanta.egg-info/PKG-INFO
fanta.egg-info/SOURCES.txt
fanta.egg-info/dependency_links.txt
fanta.egg-info/requires.txt
fanta.egg-info/top_level.txt
fanta/ext/__init__.py
fanta/ext/commands/__init__.py
fanta/ext/commands/bot.py
fanta/ext/commands/retext.py
fanta/ext/typing/__init__.py
fanta/ext/typing/context.py