Metadata-Version: 2.1
Name: fanta
Version: 0.1.0
Summary: Pythonic API Wrapper For Discord
Home-page: https://github.com/RPSMain/speedcord
Author: RPSMain
License: MIT
Platform: UNKNOWN
Requires-Python: >=3.8
License-File: LICENCE
